vemail.py
emailbook_verification-1.0.0.dist-info/METADATA
emailbook_verification-1.0.0.dist-info/WHEEL
emailbook_verification-1.0.0.dist-info/entry_points.txt
emailbook_verification-1.0.0.dist-info/top_level.txt
emailbook_verification-1.0.0.dist-info/RECORD
